jraphx/__init__.py
jraphx/py.typed
jraphx/data/__init__.py
jraphx/data/batch.py
jraphx/data/data.py
jraphx/nn/__init__.py
jraphx/nn/conv/__init__.py
jraphx/nn/conv/edge_conv.py
jraphx/nn/conv/gat_conv.py
jraphx/nn/conv/gatv2_conv.py
jraphx/nn/conv/gcn_conv.py
jraphx/nn/conv/gin_conv.py
jraphx/nn/conv/message_passing.py
jraphx/nn/conv/sage_conv.py
jraphx/nn/conv/transformer_conv.py
jraphx/nn/models/__init__.py
jraphx/nn/models/basic_gnn.py
jraphx/nn/models/gnn.py
jraphx/nn/models/jumping_knowledge.py
jraphx/nn/models/mlp.py
jraphx/nn/norm/__init__.py
jraphx/nn/norm/batch_norm.py
jraphx/nn/norm/graph_norm.py
jraphx/nn/norm/layer_norm.py
jraphx/nn/pool/__init__.py
jraphx/nn/pool/glob.py
jraphx/nn/pool/topk_pool.py
jraphx/utils/__init__.py
jraphx/utils/coalesce.py
jraphx/utils/convert.py
jraphx/utils/degree.py
jraphx/utils/loop.py
jraphx/utils/num_nodes.py
jraphx/utils/scatter.py
jraphx/utils/scatter_softmax.py
jraphx-0.0.3.dist-info/licenses/LICENSE
jraphx-0.0.3.dist-info/METADATA
jraphx-0.0.3.dist-info/WHEEL
jraphx-0.0.3.dist-info/top_level.txt
jraphx-0.0.3.dist-info/RECORD
